cellphase/__init__.py
cellphase/cellphase_batch_predict.py
cellphase/cellphase_roi_export.py
cellphase/explore_params.py
cellphase-0.1.2.dist-info/METADATA
cellphase-0.1.2.dist-info/WHEEL
cellphase-0.1.2.dist-info/top_level.txt
cellphase-0.1.2.dist-info/RECORD
