Metadata-Version: 2.4
Name: cellphase
Version: 0.1.2
Summary: CellPhase: QPI-focused cell segmentation utilities
Author: Sourya Sengupta
Classifier: Programming Language :: Python :: 3
Classifier: License :: OSI Approved :: MIT License
Classifier: Operating System :: OS Independent
Classifier: Intended Audience :: Science/Research
Classifier: Topic :: Scientific/Engineering :: Artificial Intelligence
Requires-Python: >=3.9
Requires-Dist: numpy<2
Requires-Dist: scipy
Requires-Dist: matplotlib
Requires-Dist: tqdm
Requires-Dist: scikit-image
Requires-Dist: pillow
Requires-Dist: cellpose==3.1.1
Requires-Dist: opencv-python-headless==4.8.0.76
Requires-Dist: tifffile
Requires-Dist: roifile
Requires-Dist: notebook
Requires-Dist: ipykernel
Requires-Dist: ipywidgets
Dynamic: author
Dynamic: classifier
Dynamic: description
Dynamic: description-content-type
Dynamic: requires-dist
Dynamic: requires-python
Dynamic: summary
